AUTHORS.rst
HISTORY.rst
LICENSE.rst
MANIFEST.in
README.rst
setup.py
mofa/__init__.py
mofa/_algorithms.c
mofa/foo.py
mofa/mofa.py
mofa/profilefoo.py
mofa/psis_ex.py
mofa/test.py
mofa.egg-info/PKG-INFO
mofa.egg-info/SOURCES.txt
mofa.egg-info/dependency_links.txt
mofa.egg-info/requires.txt
mofa.egg-info/top_level.txt
test/test.py