Metadata-Version: 1.1
Name: mofa
Version: 0.0.2a
Summary: Mixture of factor analyzers
Home-page: https://github.com/rossfadely/mofa
Author: Ross Fadely, David W. Hogg & Dan Foreman-Mackey
Author-email: UNKNOWN
License: MIT
Platform: UNKNOWN
Classifier: Development Status :: 3 - Alpha
Classifier: Intended Audience :: Developers
Classifier: Intended Audience :: Science/Research
Classifier: Operating System :: OS Independent
Classifier: Programming Language :: Python
